lshid/__init__.py
lshid/__main__.py
lshid-0.2.2.dist-info/LICENSE
lshid-0.2.2.dist-info/METADATA
lshid-0.2.2.dist-info/WHEEL
lshid-0.2.2.dist-info/entry_points.txt
lshid-0.2.2.dist-info/top_level.txt
lshid-0.2.2.dist-info/RECORD
