Metadata-Version: 2.1
Name: lshid
Version: 0.2.2
Summary: UNKNOWN
Home-page: https://github.com/FFY00/lshid
Author: Filipe Laíns
Author-email: lains@archlinux.org
License: MIT
Platform: UNKNOWN
Classifier: License :: OSI Approved :: MIT License
Classifier: Programming Language :: Python :: 3.6
Classifier: Programming Language :: Python :: 3.7
Classifier: Programming Language :: Python :: 3.8
Classifier: Topic :: System :: Operating System Kernels :: Linux
Requires-Python: <4,>=3.6
Requires-Dist: ioctl
Requires-Dist: hid-parser (~=0.0.2)
Provides-Extra: filter
Requires-Dist: parse ; extra == 'filter'
